client/__init__.py
client/client.py
subscriptions/__init__.py
subscriptions/addon.py
subscriptions/customer.py
subscriptions/hostedpage.py
subscriptions/invoice.py
subscriptions/plan.py
subscriptions/subscription.py
utils/__init__.py
utils/constants.py
subscriptions-1.0.1.dist-info/METADATA
subscriptions-1.0.1.dist-info/WHEEL
subscriptions-1.0.1.dist-info/top_level.txt
subscriptions-1.0.1.dist-info/RECORD
