Metadata-Version: 2.1
Name: subscriptions
Version: 1.0.1
Summary: A simple python wrapper for the Zoho subscription API compatible with Python 3.7
Home-page: https://github.com/competition-index/ci-zoho-subscription
Author: Quintus Labs
License: MIT
Keywords: Firebase,Python 3
Platform: UNKNOWN
Classifier: Development Status :: 3 - Alpha
Classifier: Intended Audience :: Developers
Classifier: License :: OSI Approved :: MIT License
Classifier: Programming Language :: Python :: 3.5
